<?xml version="1.0"?>
<fsimage>
    <version>
        <layoutVersion>-64</layoutVersion>
        <onDiskVersion>1</onDiskVersion>
        <oivRevision>ba631c436b806728f8ec2f54ab1e289526c90579</oivRevision>
    </version>
    <NameSection>
        <namespaceId>1407160188</namespaceId>
        <genstampV1>1000</genstampV1>
        <genstampV2>1094</genstampV2>
        <genstampV1Limit>0</genstampV1Limit>
        <lastAllocatedBlockId>1073741917</lastAllocatedBlockId>
        <txid>909</txid>
    </NameSection>
    <ErasureCodingSection>
        <erasureCodingPolicy>
            <policyId>1</policyId>
            <policyName>RS-6-3-1024k</policyName>
            <cellSize>1048576</cellSize>
            <policyState>DISABLED</policyState>
            <ecSchema>
                <codecName>rs</codecName>
                <dataUnits>6</dataUnits>
                <parityUnits>3</parityUnits>
            </ecSchema>
        </erasureCodingPolicy>

        <erasureCodingPolicy>
            <policyId>2</policyId>
            <policyName>RS-3-2-1024k</policyName>
            <cellSize>1048576</cellSize>
            <policyState>DISABLED</policyState>
            <ecSchema>
                <codecName>rs</codecName>
                <dataUnits>3</dataUnits>
                <parityUnits>2</parityUnits>
            </ecSchema>
        </erasureCodingPolicy>

        <erasureCodingPolicy>
            <policyId>3</policyId>
            <policyName>RS-LEGACY-6-3-1024k</policyName>
            <cellSize>1048576</cellSize>
            <policyState>DISABLED</policyState>
            <ecSchema>
                <codecName>rs-legacy</codecName>
                <dataUnits>6</dataUnits>
                <parityUnits>3</parityUnits>
            </ecSchema>
        </erasureCodingPolicy>

        <erasureCodingPolicy>
            <policyId>4</policyId>
            <policyName>XOR-2-1-1024k</policyName>
            <cellSize>1048576</cellSize>
            <policyState>DISABLED</policyState>
            <ecSchema>
                <codecName>xor</codecName>
                <dataUnits>2</dataUnits>
                <parityUnits>1</parityUnits>
            </ecSchema>
        </erasureCodingPolicy>

        <erasureCodingPolicy>
            <policyId>5</policyId>
            <policyName>RS-10-4-1024k</policyName>
            <cellSize>1048576</cellSize>
            <policyState>DISABLED</policyState>
            <ecSchema>
                <codecName>rs</codecName>
                <dataUnits>10</dataUnits>
                <parityUnits>4</parityUnits>
            </ecSchema>
        </erasureCodingPolicy>

    </ErasureCodingSection>

    <INodeSection>
        <lastInodeId>16581</lastInodeId>
        <numInodes>54</numInodes>
        <inode>
            <id>16385</id>
            <type>DIRECTORY</type>
            <name></name>
            <mtime>1636086510477</mtime>
            <permission>yzzer:supergroup:0755</permission>
            <nsquota>9223372036854775807</nsquota>
            <dsquota>-1</dsquota>
        </inode>
        <inode>
            <id>16386</id>
            <type>DIRECTORY</type>
            <name>wcinput</name>
            <mtime>1636035211456</mtime>
            <permission>yzzer:supergroup:0755</permission>
            <nsquota>-1</nsquota>
            <dsquota>-1</dsquota>
        </inode>
        <inode>
            <id>16387</id>
            <type>FILE</type>
            <name>hello.txt</name>
            <replication>2</replication>
            <mtime>1636022727231</mtime>
            <atime>1636086431495</atime>
            <preferredBlockSize>134217728</preferredBlockSize>
            <permission>yzzer:supergroup:0644</permission>
            <blocks>
                <block>
                    <id>1073741825</id>
                    <genstamp>1036</genstamp>
                    <numBytes>140</numBytes>
                </block>
            </blocks>
            <storagePolicyId>0</storagePolicyId>
        </inode>
        <inode>
            <id>16464</id>
            <type>FILE</type>
            <name>newFile.txt</name>
            <replication>2</replication>
            <mtime>1636022455145</mtime>
            <atime>1636086430646</atime>
            <preferredBlockSize>134217728</preferredBlockSize>
            <permission>yzzer:supergroup:0644</permission>
            <blocks>
                <block>
                    <id>1073741858</id>
                    <genstamp>1034</genstamp>
                    <numBytes>61</numBytes>
                </block>
            </blocks>
            <storagePolicyId>0</storagePolicyId>
        </inode>
        <inode>
            <id>16466</id>
            <type>FILE</type>
            <name>haha.txt</name>
            <replication>2</replication>
            <mtime>1636022824197</mtime>
            <atime>1636085773553</atime>
            <preferredBlockSize>134217728</preferredBlockSize>
            <permission>yzzer:supergroup:0666</permission>
            <blocks>
                <block>
                    <id>1073741860</id>
                    <genstamp>1037</genstamp>
                    <numBytes>32</numBytes>
                </block>
            </blocks>
            <storagePolicyId>0</storagePolicyId>
        </inode>
        <inode>
            <id>16467</id>
            <type>DIRECTORY</type>
            <name>system</name>
            <mtime>1636024604710</mtime>
            <permission>yzzer:supergroup:0755</permission>
            <nsquota>-1</nsquota>
            <dsquota>-1</dsquota>
        </inode>
        <inode>
            <id>16469</id>
            <type>DIRECTORY</type>
            <name>client_test</name>
            <mtime>1636035226746</mtime>
            <permission>yzzer:supergroup:0755</permission>
            <nsquota>-1</nsquota>
            <dsquota>-1</dsquota>
        </inode>
        <inode>
            <id>16471</id>
            <type>DIRECTORY</type>
            <name>tmp</name>
            <mtime>1636033323579</mtime>
            <permission>yzzer:supergroup:0770</permission>
            <nsquota>-1</nsquota>
            <dsquota>-1</dsquota>
        </inode>
        <inode>
            <id>16472</id>
            <type>DIRECTORY</type>
            <name>hadoop-yarn</name>
            <mtime>1636032880357</mtime>
            <permission>yzzer:supergroup:0770</permission>
            <nsquota>-1</nsquota>
            <dsquota>-1</dsquota>
        </inode>
        <inode>
            <id>16473</id>
            <type>DIRECTORY</type>
            <name>staging</name>
            <mtime>1636033320642</mtime>
            <permission>yzzer:supergroup:0770</permission>
            <nsquota>-1</nsquota>
            <dsquota>-1</dsquota>
        </inode>
        <inode>
            <id>16474</id>
            <type>DIRECTORY</type>
            <name>history</name>
            <mtime>1636032880388</mtime>
            <permission>yzzer:supergroup:0770</permission>
            <nsquota>-1</nsquota>
            <dsquota>-1</dsquota>
        </inode>
        <inode>
            <id>16475</id>
            <type>DIRECTORY</type>
            <name>done</name>
            <mtime>1636033351553</mtime>
            <permission>yzzer:supergroup:0770</permission>
            <nsquota>-1</nsquota>
            <dsquota>-1</dsquota>
        </inode>
        <inode>
            <id>16476</id>
            <type>DIRECTORY</type>
            <name>done_intermediate</name>
            <mtime>1636033325604</mtime>
            <permission>yzzer:supergroup:1777</permission>
            <nsquota>-1</nsquota>
            <dsquota>-1</dsquota>
        </inode>
        <inode>
            <id>16477</id>
            <type>DIRECTORY</type>
            <name>yzzer</name>
            <mtime>1636033320643</mtime>
            <permission>yzzer:supergroup:0700</permission>
            <nsquota>-1</nsquota>
            <dsquota>-1</dsquota>
        </inode>
        <inode>
            <id>16478</id>
            <type>DIRECTORY</type>
            <name>.staging</name>
            <mtime>1636086520352</mtime>
            <permission>yzzer:supergroup:0700</permission>
            <nsquota>-1</nsquota>
            <dsquota>-1</dsquota>
        </inode>
        <inode>
            <id>16484</id>
            <type>DIRECTORY</type>
            <name>logs</name>
            <mtime>1636033323609</mtime>
            <permission>yzzer:yzzer:1777</permission>
            <nsquota>-1</nsquota>
            <dsquota>-1</dsquota>
        </inode>
        <inode>
            <id>16485</id>
            <type>DIRECTORY</type>
            <name>yzzer</name>
            <mtime>1636033323611</mtime>
            <permission>yzzer:yzzer:0770</permission>
            <nsquota>-1</nsquota>
            <dsquota>-1</dsquota>
        </inode>
        <inode>
            <id>16486</id>
            <type>DIRECTORY</type>
            <name>logs-tfile</name>
            <mtime>1636086507248</mtime>
            <permission>yzzer:yzzer:0770</permission>
            <nsquota>-1</nsquota>
            <dsquota>-1</dsquota>
        </inode>
        <inode>
            <id>16487</id>
            <type>DIRECTORY</type>
            <name>application_1636032924248_0001</name>
            <mtime>1636033349345</mtime>
            <permission>yzzer:yzzer:0770</permission>
            <nsquota>-1</nsquota>
            <dsquota>-1</dsquota>
        </inode>
        <inode>
            <id>16488</id>
            <type>DIRECTORY</type>
            <name>yzzer</name>
            <mtime>1636086570282</mtime>
            <permission>yzzer:supergroup:0770</permission>
            <nsquota>-1</nsquota>
            <dsquota>-1</dsquota>
        </inode>
        <inode>
            <id>16501</id>
            <type>FILE</type>
            <name>
                job_1636032924248_0001-1636033322153-yzzer-word+count-1636033341692-3-1-SUCCEEDED-default-1636033328021.jhist
            </name>
            <replication>2</replication>
            <mtime>1636033341777</mtime>
            <atime>1636033341753</atime>
            <preferredBlockSize>134217728</preferredBlockSize>
            <permission>yzzer:supergroup:0770</permission>
            <blocks>
                <block>
                    <id>1073741873</id>
                    <genstamp>1050</genstamp>
                    <numBytes>29649</numBytes>
                </block>
            </blocks>
            <storagePolicyId>0</storagePolicyId>
        </inode>
        <inode>
            <id>16502</id>
            <type>FILE</type>
            <name>job_1636032924248_0001_conf.xml</name>
            <replication>2</replication>
            <mtime>1636033341807</mtime>
            <atime>1636033341785</atime>
            <preferredBlockSize>134217728</preferredBlockSize>
            <permission>yzzer:supergroup:0770</permission>
            <blocks>
                <block>
                    <id>1073741874</id>
                    <genstamp>1051</genstamp>
                    <numBytes>214909</numBytes>
                </block>
            </blocks>
            <storagePolicyId>0</storagePolicyId>
        </inode>
        <inode>
            <id>16503</id>
            <type>FILE</type>
            <name>master_34103</name>
            <replication>2</replication>
            <mtime>1636033348837</mtime>
            <atime>1636033348766</atime>
            <preferredBlockSize>134217728</preferredBlockSize>
            <permission>yzzer:yzzer:0640</permission>
            <blocks>
                <block>
                    <id>1073741875</id>
                    <genstamp>1052</genstamp>
                    <numBytes>95456</numBytes>
                </block>
            </blocks>
            <storagePolicyId>0</storagePolicyId>
        </inode>
        <inode>
            <id>16504</id>
            <type>FILE</type>
            <name>slave02_35253</name>
            <replication>2</replication>
            <mtime>1636033349340</mtime>
            <atime>1636033349262</atime>
            <preferredBlockSize>134217728</preferredBlockSize>
            <permission>yzzer:yzzer:0640</permission>
            <blocks>
                <block>
                    <id>1073741876</id>
                    <genstamp>1053</genstamp>
                    <numBytes>113745</numBytes>
                </block>
            </blocks>
            <storagePolicyId>0</storagePolicyId>
        </inode>
        <inode>
            <id>16505</id>
            <type>DIRECTORY</type>
            <name>2021</name>
            <mtime>1636033351553</mtime>
            <permission>yzzer:supergroup:0770</permission>
            <nsquota>-1</nsquota>
            <dsquota>-1</dsquota>
        </inode>
        <inode>
            <id>16506</id>
            <type>DIRECTORY</type>
            <name>11</name>
            <mtime>1636086570274</mtime>
            <permission>yzzer:supergroup:0770</permission>
            <nsquota>-1</nsquota>
            <dsquota>-1</dsquota>
        </inode>
        <inode>
            <id>16507</id>
            <type>DIRECTORY</type>
            <name>04</name>
            <mtime>1636033351553</mtime>
            <permission>yzzer:supergroup:0770</permission>
            <nsquota>-1</nsquota>
            <dsquota>-1</dsquota>
        </inode>
        <inode>
            <id>16508</id>
            <type>DIRECTORY</type>
            <name>000000</name>
            <mtime>1636033470279</mtime>
            <permission>yzzer:supergroup:0770</permission>
            <nsquota>-1</nsquota>
            <dsquota>-1</dsquota>
        </inode>
        <inode>
            <id>16515</id>
            <type>DIRECTORY</type>
            <name>application_1636032924248_0002</name>
            <mtime>1636033474252</mtime>
            <permission>yzzer:yzzer:0770</permission>
            <nsquota>-1</nsquota>
            <dsquota>-1</dsquota>
        </inode>
        <inode>
            <id>16528</id>
            <type>FILE</type>
            <name>
                job_1636032924248_0002-1636033452611-yzzer-word+count-1636033466598-3-1-SUCCEEDED-default-1636033457751.jhist
            </name>
            <replication>2</replication>
            <mtime>1636033466719</mtime>
            <atime>1636033466696</atime>
            <preferredBlockSize>134217728</preferredBlockSize>
            <permission>yzzer:supergroup:0770</permission>
            <blocks>
                <block>
                    <id>1073741886</id>
                    <genstamp>1063</genstamp>
                    <numBytes>29608</numBytes>
                </block>
            </blocks>
            <storagePolicyId>0</storagePolicyId>
        </inode>
        <inode>
            <id>16529</id>
            <type>FILE</type>
            <name>job_1636032924248_0002_conf.xml</name>
            <replication>2</replication>
            <mtime>1636033466749</mtime>
            <atime>1636033466728</atime>
            <preferredBlockSize>134217728</preferredBlockSize>
            <permission>yzzer:supergroup:0770</permission>
            <blocks>
                <block>
                    <id>1073741887</id>
                    <genstamp>1064</genstamp>
                    <numBytes>214909</numBytes>
                </block>
            </blocks>
            <storagePolicyId>0</storagePolicyId>
        </inode>
        <inode>
            <id>16530</id>
            <type>FILE</type>
            <name>master_34103</name>
            <replication>2</replication>
            <mtime>1636033473778</mtime>
            <atime>1636033473740</atime>
            <preferredBlockSize>134217728</preferredBlockSize>
            <permission>yzzer:yzzer:0640</permission>
            <blocks>
                <block>
                    <id>1073741888</id>
                    <genstamp>1065</genstamp>
                    <numBytes>63729</numBytes>
                </block>
            </blocks>
            <storagePolicyId>0</storagePolicyId>
        </inode>
        <inode>
            <id>16531</id>
            <type>FILE</type>
            <name>slave02_35253</name>
            <replication>2</replication>
            <mtime>1636033473839</mtime>
            <atime>1636033473817</atime>
            <preferredBlockSize>134217728</preferredBlockSize>
            <permission>yzzer:yzzer:0640</permission>
            <blocks>
                <block>
                    <id>1073741889</id>
                    <genstamp>1066</genstamp>
                    <numBytes>35764</numBytes>
                </block>
            </blocks>
            <storagePolicyId>0</storagePolicyId>
        </inode>
        <inode>
            <id>16532</id>
            <type>FILE</type>
            <name>slave01_44195</name>
            <replication>2</replication>
            <mtime>1636033474248</mtime>
            <atime>1636033474175</atime>
            <preferredBlockSize>134217728</preferredBlockSize>
            <permission>yzzer:yzzer:0640</permission>
            <blocks>
                <block>
                    <id>1073741890</id>
                    <genstamp>1067</genstamp>
                    <numBytes>109826</numBytes>
                </block>
            </blocks>
            <storagePolicyId>0</storagePolicyId>
        </inode>
        <inode>
            <id>16534</id>
            <type>FILE</type>
            <name>test2.txt</name>
            <replication>3</replication>
            <mtime>1636033926355</mtime>
            <atime>1636033922515</atime>
            <preferredBlockSize>134217728</preferredBlockSize>
            <permission>yzzer:supergroup:0644</permission>
            <blocks>
                <block>
                    <id>1073741892</id>
                    <genstamp>1069</genstamp>
                    <numBytes>1178</numBytes>
                </block>
            </blocks>
            <storagePolicyId>0</storagePolicyId>
        </inode>
        <inode>
            <id>16540</id>
            <type>DIRECTORY</type>
            <name>application_1636032924248_0003</name>
            <mtime>1636086442537</mtime>
            <permission>yzzer:yzzer:0770</permission>
            <nsquota>-1</nsquota>
            <dsquota>-1</dsquota>
        </inode>
        <inode>
            <id>16541</id>
            <type>DIRECTORY</type>
            <name>wcoutput</name>
            <mtime>1636086434952</mtime>
            <permission>yzzer:supergroup:0755</permission>
            <nsquota>-1</nsquota>
            <dsquota>-1</dsquota>
        </inode>
        <inode>
            <id>16548</id>
            <type>FILE</type>
            <name>part-r-00000</name>
            <replication>2</replication>
            <mtime>1636086434883</mtime>
            <atime>1636086434785</atime>
            <preferredBlockSize>134217728</preferredBlockSize>
            <permission>yzzer:supergroup:0644</permission>
            <blocks>
                <block>
                    <id>1073741899</id>
                    <genstamp>1076</genstamp>
                    <numBytes>192</numBytes>
                </block>
            </blocks>
            <storagePolicyId>0</storagePolicyId>
        </inode>
        <inode>
            <id>16550</id>
            <type>FILE</type>
            <name>_SUCCESS</name>
            <replication>2</replication>
            <mtime>1636086434955</mtime>
            <atime>1636086434952</atime>
            <preferredBlockSize>134217728</preferredBlockSize>
            <permission>yzzer:supergroup:0644</permission>
            <storagePolicyId>0</storagePolicyId>
        </inode>
        <inode>
            <id>16553</id>
            <type>FILE</type>
            <name>
                job_1636032924248_0003-1636086419402-yzzer-word+count-1636086434959-3-1-SUCCEEDED-default-1636086423713.jhist
            </name>
            <replication>2</replication>
            <mtime>1636086435035</mtime>
            <atime>1636086435019</atime>
            <preferredBlockSize>134217728</preferredBlockSize>
            <permission>yzzer:supergroup:0770</permission>
            <blocks>
                <block>
                    <id>1073741901</id>
                    <genstamp>1078</genstamp>
                    <numBytes>29915</numBytes>
                </block>
            </blocks>
            <storagePolicyId>0</storagePolicyId>
        </inode>
        <inode>
            <id>16554</id>
            <type>FILE</type>
            <name>job_1636032924248_0003_conf.xml</name>
            <replication>2</replication>
            <mtime>1636086435065</mtime>
            <atime>1636086435046</atime>
            <preferredBlockSize>134217728</preferredBlockSize>
            <permission>yzzer:supergroup:0770</permission>
            <blocks>
                <block>
                    <id>1073741902</id>
                    <genstamp>1079</genstamp>
                    <numBytes>214909</numBytes>
                </block>
            </blocks>
            <storagePolicyId>0</storagePolicyId>
        </inode>
        <inode>
            <id>16555</id>
            <type>FILE</type>
            <name>slave01_44195</name>
            <replication>2</replication>
            <mtime>1636086442166</mtime>
            <atime>1636086442136</atime>
            <preferredBlockSize>134217728</preferredBlockSize>
            <permission>yzzer:yzzer:0640</permission>
            <blocks>
                <block>
                    <id>1073741903</id>
                    <genstamp>1080</genstamp>
                    <numBytes>95414</numBytes>
                </block>
            </blocks>
            <storagePolicyId>0</storagePolicyId>
        </inode>
        <inode>
            <id>16556</id>
            <type>FILE</type>
            <name>slave02_35253</name>
            <replication>2</replication>
            <mtime>1636086442535</mtime>
            <atime>1636086442499</atime>
            <preferredBlockSize>134217728</preferredBlockSize>
            <permission>yzzer:yzzer:0640</permission>
            <blocks>
                <block>
                    <id>1073741904</id>
                    <genstamp>1081</genstamp>
                    <numBytes>114653</numBytes>
                </block>
            </blocks>
            <storagePolicyId>0</storagePolicyId>
        </inode>
        <inode>
            <id>16562</id>
            <type>DIRECTORY</type>
            <name>application_1636032924248_0004</name>
            <mtime>1636086526770</mtime>
            <permission>yzzer:yzzer:0770</permission>
            <nsquota>-1</nsquota>
            <dsquota>-1</dsquota>
        </inode>
        <inode>
            <id>16564</id>
            <type>DIRECTORY</type>
            <name>wcoutput2</name>
            <mtime>1636086519225</mtime>
            <permission>yzzer:supergroup:0755</permission>
            <nsquota>-1</nsquota>
            <dsquota>-1</dsquota>
        </inode>
        <inode>
            <id>16570</id>
            <type>FILE</type>
            <name>part-r-00000</name>
            <replication>2</replication>
            <mtime>1636086519158</mtime>
            <atime>1636086519065</atime>
            <preferredBlockSize>134217728</preferredBlockSize>
            <permission>yzzer:supergroup:0644</permission>
            <blocks>
                <block>
                    <id>1073741911</id>
                    <genstamp>1088</genstamp>
                    <numBytes>192</numBytes>
                </block>
            </blocks>
            <storagePolicyId>0</storagePolicyId>
        </inode>
        <inode>
            <id>16572</id>
            <type>FILE</type>
            <name>_SUCCESS</name>
            <replication>2</replication>
            <mtime>1636086519227</mtime>
            <atime>1636086519225</atime>
            <preferredBlockSize>134217728</preferredBlockSize>
            <permission>yzzer:supergroup:0644</permission>
            <storagePolicyId>0</storagePolicyId>
        </inode>
        <inode>
            <id>16575</id>
            <type>FILE</type>
            <name>
                job_1636032924248_0004-1636086506825-yzzer-word+count-1636086519232-3-1-SUCCEEDED-default-1636086510464.jhist
            </name>
            <replication>2</replication>
            <mtime>1636086519296</mtime>
            <atime>1636086519280</atime>
            <preferredBlockSize>134217728</preferredBlockSize>
            <permission>yzzer:supergroup:0770</permission>
            <blocks>
                <block>
                    <id>1073741913</id>
                    <genstamp>1090</genstamp>
                    <numBytes>29621</numBytes>
                </block>
            </blocks>
            <storagePolicyId>0</storagePolicyId>
        </inode>
        <inode>
            <id>16576</id>
            <type>FILE</type>
            <name>job_1636032924248_0004_conf.xml</name>
            <replication>2</replication>
            <mtime>1636086519321</mtime>
            <atime>1636086519303</atime>
            <preferredBlockSize>134217728</preferredBlockSize>
            <permission>yzzer:supergroup:0770</permission>
            <blocks>
                <block>
                    <id>1073741914</id>
                    <genstamp>1091</genstamp>
                    <numBytes>214910</numBytes>
                </block>
            </blocks>
            <storagePolicyId>0</storagePolicyId>
        </inode>
        <inode>
            <id>16577</id>
            <type>FILE</type>
            <name>slave01_44195</name>
            <replication>2</replication>
            <mtime>1636086526292</mtime>
            <atime>1636086526260</atime>
            <preferredBlockSize>134217728</preferredBlockSize>
            <permission>yzzer:yzzer:0640</permission>
            <blocks>
                <block>
                    <id>1073741915</id>
                    <genstamp>1092</genstamp>
                    <numBytes>63750</numBytes>
                </block>
            </blocks>
            <storagePolicyId>0</storagePolicyId>
        </inode>
        <inode>
            <id>16578</id>
            <type>FILE</type>
            <name>slave02_35253</name>
            <replication>2</replication>
            <mtime>1636086526394</mtime>
            <atime>1636086526369</atime>
            <preferredBlockSize>134217728</preferredBlockSize>
            <permission>yzzer:yzzer:0640</permission>
            <blocks>
                <block>
                    <id>1073741916</id>
                    <genstamp>1093</genstamp>
                    <numBytes>35745</numBytes>
                </block>
            </blocks>
            <storagePolicyId>0</storagePolicyId>
        </inode>
        <inode>
            <id>16579</id>
            <type>FILE</type>
            <name>master_34103</name>
            <replication>2</replication>
            <mtime>1636086526767</mtime>
            <atime>1636086526736</atime>
            <preferredBlockSize>134217728</preferredBlockSize>
            <permission>yzzer:yzzer:0640</permission>
            <blocks>
                <block>
                    <id>1073741917</id>
                    <genstamp>1094</genstamp>
                    <numBytes>109862</numBytes>
                </block>
            </blocks>
            <storagePolicyId>0</storagePolicyId>
        </inode>
        <inode>
            <id>16580</id>
            <type>DIRECTORY</type>
            <name>05</name>
            <mtime>1636086570275</mtime>
            <permission>yzzer:supergroup:0770</permission>
            <nsquota>-1</nsquota>
            <dsquota>-1</dsquota>
        </inode>
        <inode>
            <id>16581</id>
            <type>DIRECTORY</type>
            <name>000000</name>
            <mtime>1636086570282</mtime>
            <permission>yzzer:supergroup:0770</permission>
            <nsquota>-1</nsquota>
            <dsquota>-1</dsquota>
        </inode>
    </INodeSection>
    <INodeReferenceSection></INodeReferenceSection>
    <SnapshotSection>
        <snapshotCounter>0</snapshotCounter>
        <numSnapshots>0</numSnapshots>
    </SnapshotSection>
    <INodeDirectorySection>
        <directory>
            <parent>16385</parent>
            <child>16469</child>
            <child>16467</child>
            <child>16471</child>
            <child>16386</child>
            <child>16541</child>
            <child>16564</child>
        </directory>
        <directory>
            <parent>16386</parent>
            <child>16466</child>
            <child>16387</child>
            <child>16464</child>
        </directory>
        <directory>
            <parent>16469</parent>
            <child>16534</child>
        </directory>
        <directory>
            <parent>16471</parent>
            <child>16472</child>
            <child>16484</child>
        </directory>
        <directory>
            <parent>16472</parent>
            <child>16473</child>
        </directory>
        <directory>
            <parent>16473</parent>
            <child>16474</child>
            <child>16477</child>
        </directory>
        <directory>
            <parent>16474</parent>
            <child>16475</child>
            <child>16476</child>
        </directory>
        <directory>
            <parent>16475</parent>
            <child>16505</child>
        </directory>
        <directory>
            <parent>16476</parent>
            <child>16488</child>
        </directory>
        <directory>
            <parent>16477</parent>
            <child>16478</child>
        </directory>
        <directory>
            <parent>16484</parent>
            <child>16485</child>
        </directory>
        <directory>
            <parent>16485</parent>
            <child>16486</child>
        </directory>
        <directory>
            <parent>16486</parent>
            <child>16487</child>
            <child>16515</child>
            <child>16540</child>
            <child>16562</child>
        </directory>
        <directory>
            <parent>16487</parent>
            <child>16503</child>
            <child>16504</child>
        </directory>
        <directory>
            <parent>16505</parent>
            <child>16506</child>
        </directory>
        <directory>
            <parent>16506</parent>
            <child>16507</child>
            <child>16580</child>
        </directory>
        <directory>
            <parent>16507</parent>
            <child>16508</child>
        </directory>
        <directory>
            <parent>16508</parent>
            <child>16501</child>
            <child>16502</child>
            <child>16528</child>
            <child>16529</child>
        </directory>
        <directory>
            <parent>16515</parent>
            <child>16530</child>
            <child>16532</child>
            <child>16531</child>
        </directory>
        <directory>
            <parent>16540</parent>
            <child>16555</child>
            <child>16556</child>
        </directory>
        <directory>
            <parent>16541</parent>
            <child>16550</child>
            <child>16548</child>
        </directory>
        <directory>
            <parent>16562</parent>
            <child>16579</child>
            <child>16577</child>
            <child>16578</child>
        </directory>
        <directory>
            <parent>16564</parent>
            <child>16572</child>
            <child>16570</child>
        </directory>
        <directory>
            <parent>16580</parent>
            <child>16581</child>
        </directory>
        <directory>
            <parent>16581</parent>
            <child>16553</child>
            <child>16554</child>
            <child>16575</child>
            <child>16576</child>
        </directory>
    </INodeDirectorySection>
    <FileUnderConstructionSection></FileUnderConstructionSection>
    <SecretManagerSection>
        <currentId>0</currentId>
        <tokenSequenceNumber>0</tokenSequenceNumber>
        <numDelegationKeys>0</numDelegationKeys>
        <numTokens>0</numTokens>
    </SecretManagerSection>
    <CacheManagerSection>
        <nextDirectiveId>1</nextDirectiveId>
        <numDirectives>0</numDirectives>
        <numPools>0</numPools>
    </CacheManagerSection>
</fsimage>
